augme/__init__.py
augme/assets/audio/silent.flac
augme/assets/fonts/NotoSansTC-Black.otf
augme/assets/fonts/NotoSansTC-Bold.otf
augme/assets/fonts/NotoSansTC-Light.otf
augme/assets/fonts/NotoSansTC-Medium.otf
augme/assets/fonts/NotoSansTC-Regular.otf
augme/assets/fonts/NotoSansTC-Thin.otf
augme/assets/masks/dfdc_mask.png
augme/assets/masks/square.png
augme/assets/text/Longman_Communication_3000.txt
augme/assets/text/RU_10000.txt
augme/assets/text/TOCFL_7517.txt
augme/assets/twemojis/activity/american_football.png
augme/assets/twemojis/activity/artist_palette.png
augme/assets/twemojis/activity/balloon.png
augme/assets/twemojis/activity/baseball.png
augme/assets/twemojis/activity/basketball.png
augme/assets/twemojis/activity/bowling.png
augme/assets/twemojis/activity/carp_streamer.png
augme/assets/twemojis/activity/christmas_tree.png
augme/assets/twemojis/activity/circus_tent.png
augme/assets/twemojis/activity/clapper_board.png
augme/assets/twemojis/activity/club_suit.png
augme/assets/twemojis/activity/confetti_ball.png
augme/assets/twemojis/activity/crystal_ball.png
augme/assets/twemojis/activity/diamond_suit.png
augme/assets/twemojis/activity/direct_hit.png
augme/assets/twemojis/activity/fireworks.png
augme/assets/twemojis/activity/fishing_pole.png
augme/assets/twemojis/activity/flag_in_hole.png
augme/assets/twemojis/activity/game_die.png
augme/assets/twemojis/activity/guitar.png
augme/assets/twemojis/activity/headphone.png
augme/assets/twemojis/activity/heart_suit.png
augme/assets/twemojis/activity/horse_racing.png
augme/assets/twemojis/activity/jack_o_lantern.png
augme/assets/twemojis/activity/japanese_dolls.png
augme/assets/twemojis/activity/man_surfing.png
augme/assets/twemojis/activity/man_swimming.png
augme/assets/twemojis/activity/microphone.png
augme/assets/twemojis/activity/moon_viewing_ceremony.png
augme/assets/twemojis/activity/musical_keyboard.png
augme/assets/twemojis/activity/musical_score.png
augme/assets/twemojis/activity/party_popper.png
augme-0.1.0.dist-info/LICENSE
augme-0.1.0.dist-info/METADATA
augme-0.1.0.dist-info/WHEEL
augme-0.1.0.dist-info/top_level.txt
augme-0.1.0.dist-info/RECORD
