Metadata-Version: 2.1
Name: augme
Version: 0.1.0
Summary: Multimedia augmentations library
Home-page: https://github.com/romanak/AugMe
Author: Roman Akchurin
Author-email: me@romanakchurin.com
Project-URL: Bug Tracker, https://github.com/romanak/AugMe/issues
Project-URL: repository, https://github.com/romanak/AugMe
Classifier: Programming Language :: Python :: 3
Classifier: License :: OSI Approved :: MIT License
Classifier: Operating System :: OS Independent
Requires-Python: >=3.6
License-File: LICENSE
Requires-Dist: numpy (>=1.19.5)
Requires-Dist: Pillow (>=9.0.0)
